{
  "indicator": "IT.CEL.SETS.P2",
  "indicator_name": "Mobile cellular subscriptions (per 100 people)",
  "data": [
    {
      "year": 2010,
      "value": 64.8154,
      "indicator": "IT.CEL.SETS.P2",
      "indicator_name": "Mobile cellular subscriptions (per 100 people)",
      "country": "West Bank and Gaza",
      "source": "worldbank"
    },
    {
      "year": 2011,
      "value": 70.093,
      "indicator": "IT.CEL.SETS.P2",
      "indicator_name": "Mobile cellular subscriptions (per 100 people)",
      "country": "West Bank and Gaza",
      "source": "worldbank"
    },
    {
      "year": 2012,
      "value": 74.3646,
      "indicator": "IT.CEL.SETS.P2",
      "indicator_name": "Mobile cellular subscriptions (per 100 people)",
      "country": "West Bank and Gaza",
      "source": "worldbank"
    },
    {
      "year": 2013,
      "value": 73.9291,
      "indicator": "IT.CEL.SETS.P2",
      "indicator_name": "Mobile cellular subscriptions (per 100 people)",
      "country": "West Bank and Gaza",
      "source": "worldbank"
    },
    {
      "year": 2014,
      "value": 72.4102,
      "indicator": "IT.CEL.SETS.P2",
      "indicator_name": "Mobile cellular subscriptions (per 100 people)",
      "country": "West Bank and Gaza",
      "source": "worldbank"
    },
    {
      "year": 2015,
      "value": 78.0924,
      "indicator": "IT.CEL.SETS.P2",
      "indicator_name": "Mobile cellular subscriptions (per 100 people)",
      "country": "West Bank and Gaza",
      "source": "worldbank"
    },
    {
      "year": 2016,
      "value": 80.1511,
      "indicator": "IT.CEL.SETS.P2",
      "indicator_name": "Mobile cellular subscriptions (per 100 people)",
      "country": "West Bank and Gaza",
      "source": "worldbank"
    },
    {
      "year": 2017,
      "value": 84.2594,
      "indicator": "IT.CEL.SETS.P2",
      "indicator_name": "Mobile cellular subscriptions (per 100 people)",
      "country": "West Bank and Gaza",
      "source": "worldbank"
    },
    {
      "year": 2018,
      "value": 90.2055,
      "indicator": "IT.CEL.SETS.P2",
      "indicator_name": "Mobile cellular subscriptions (per 100 people)",
      "country": "West Bank and Gaza",
      "source": "worldbank"
    },
    {
      "year": 2019,
      "value": 86.7372,
      "indicator": "IT.CEL.SETS.P2",
      "indicator_name": "Mobile cellular subscriptions (per 100 people)",
      "country": "West Bank and Gaza",
      "source": "worldbank"
    },
    {
      "year": 2020,
      "value": 80.1298,
      "indicator": "IT.CEL.SETS.P2",
      "indicator_name": "Mobile cellular subscriptions (per 100 people)",
      "country": "West Bank and Gaza",
      "source": "worldbank"
    },
    {
      "year": 2021,
      "value": 78.1621,
      "indicator": "IT.CEL.SETS.P2",
      "indicator_name": "Mobile cellular subscriptions (per 100 people)",
      "country": "West Bank and Gaza",
      "source": "worldbank"
    },
    {
      "year": 2022,
      "value": 76.5666,
      "indicator": "IT.CEL.SETS.P2",
      "indicator_name": "Mobile cellular subscriptions (per 100 people)",
      "country": "West Bank and Gaza",
      "source": "worldbank"
    },
    {
      "year": 2023,
      "value": 76.6919,
      "indicator": "IT.CEL.SETS.P2",
      "indicator_name": "Mobile cellular subscriptions (per 100 people)",
      "country": "West Bank and Gaza",
      "source": "worldbank"
    }
  ],
  "metadata": {
    "source": "World Bank Open Data",
    "last_updated": "2025-10-24T18:03:33.712Z",
    "total_points": 14
  },
  "validation": {
    "qualityScore": 1,
    "completeness": 1,
    "consistency": 1,
    "accuracy": 1,
    "meetsThreshold": true,
    "errorCount": 0,
    "warningCount": 0
  }
}